{
    "odata.metadata": "https://cbpfapi.unocha.org/vo2/odata/$metadata#CBPFSummary/@Element",
    "donors": 52,
    "funds": 30,
    "contribTotalAmt": 455993276.56869996,
    "contribPaidAmt": 343801252.84999996,
    "contribPledgedAmt": 112192023.71869999,
    "allocAmt": 458583529.0,
    "underApprovalAmt": "0",
    "year": "2022",
    "projectsFunded": 221,
    "partnersFunded": 10,
    "partnersFundedByType": [
        {
            "partnerType": "International NGO",
            "partnersFunded": 0
        },
        {
            "partnerType": "National NGO",
            "partnersFunded": 0
        },
        {
            "partnerType": "Others",
            "partnersFunded": 0
        },
        {
            "partnerType": "UN Agency",
            "partnersFunded": 44646259
        }
    ]
}