{
    "odata.metadata": "https://cbpfapi.unocha.org/vo2/odata/$metadata#CBPFSummary/@Element",
    "donors": 68,
    "funds": 35,
    "contribTotalAmt": 435812065.7100001,
    "contribPaidAmt": 433457065.7100001,
    "contribPledgedAmt": 2355000.0,
    "allocAmt": 428008577.2599999,
    "underApprovalAmt": "0",
    "year": "2025",
    "projectsFunded": 255,
    "partnersFunded": 12,
    "partnersFundedByType": [
        {
            "partnerType": "International NGO",
            "partnersFunded": 0
        },
        {
            "partnerType": "National NGO",
            "partnersFunded": 0
        },
        {
            "partnerType": "Others",
            "partnersFunded": 0
        },
        {
            "partnerType": "UN Agency",
            "partnersFunded": 64222406
        }
    ]
}